softworks/NewDocViewGUI.ils
softworks/Softworks.ils
softworks/__init__.py
softworks/pyproject.toml
softworks/softworks.cdsLibMgr.il
softworks/softworks.cdsinit.ils
softworks/virtue_softworks.py
softworks/doc/Doc.data.reg
softworks/doc/Doc.ils
softworks/doc/DocImport.ils
softworks/doc/DocPDF.ils
softworks/doc/DocPPTX.ils
softworks/doc/doc.data.reg
softworks/doc/pptx.ils
softworks/html/SdmHtml.data.reg
softworks/html/SdmHtml.ils
softworks/html/htmlTemplate.html
softworks/pdf/PDF.ils
softworks/pdf/SdmPdf.data.reg
softworks/pdf/pdfTemplate.docx
softworks/pdf/pdfTemplate.pdf
softworks/pptx/PPTX.ils
softworks/pptx/SdmPptx.data.reg
softworks/pptx/pptxTemplate.pptx
softworks/python/Python.ils
softworks/python/SdmJupyterLab.ils
softworks/python/SdmPy.data.reg
softworks/python/VsCode.ils
softworks/python/markdownTemplate.md
softworks/python/moduleTemplate.py
softworks/python/notebookTemplate.ipynb
softworks/python/tomlTemplate.toml
softworks/python/yamlTemplate.yaml
softworks/skill/SdmSkill.data.reg
softworks/skill/Skill.ils
softworks/skill/skillTemplate.il
softworks/skill/skillppTemplate.ils
softworks/workspace/CodeWorkspace.ils
softworks/workspace/__init__.py
softworks/workspace/code_workspace.il
softworks/workspace/code_workspace.py
softworks/workspace/workspace_files/README.md
softworks/workspace/workspace_files/__init__.py
softworks/workspace/workspace_files/dotvscode/__init__.py
softworks/workspace/workspace_files/dotvscode/extensions.json
softworks/workspace/workspace_files/dotvscode/settings.json
softworks/xlsx/SdmXlsx.data.reg
softworks/xlsx/SdmXlsx.ils
softworks/xlsx/xlsxTemplate.xlsx
softworks-0.4.0.dist-info/entry_points.txt
softworks-0.4.0.dist-info/LICENSE
softworks-0.4.0.dist-info/WHEEL
softworks-0.4.0.dist-info/METADATA
softworks-0.4.0.dist-info/RECORD
